<?xml version="1.0" encoding="utf-8" ?>
<dwsync>
<file name="admin-bar-sprite-2x.png" server="students.acg.edu/www/" local="130802385764682107" remote="130774572000000000" Dst="2" />
<file name="arrow-pointer-blue-2x.png" server="students.acg.edu/www/" local="130802385766792228" remote="130774572000000000" Dst="2" />
<file name="admin-bar-sprite.png" server="students.acg.edu/www/" local="130802385767012241" remote="130774572000000000" Dst="2" />
<file name="arrow-pointer-blue.png" server="students.acg.edu/www/" local="130802385770072416" remote="130774572000000000" Dst="2" />
<file name="blank.gif" server="students.acg.edu/www/" local="130802385799624106" remote="130774572000000000" Dst="2" />
<file name="down_arrow-2x.gif" server="students.acg.edu/www/" local="130802385806704511" remote="130774572000000000" Dst="2" />
<file name="down_arrow.gif" server="students.acg.edu/www/" local="130802385806744513" remote="130774572000000000" Dst="2" />
<file name="icon-pointer-flag-2x.png" server="students.acg.edu/www/" local="130802385808274601" remote="130774572000000000" Dst="2" />
<file name="icon-pointer-flag.png" server="students.acg.edu/www/" local="130802385837856293" remote="130774572000000000" Dst="2" />
<file name="rss-2x.png" server="students.acg.edu/www/" local="130802385869978130" remote="130774572000000000" Dst="2" />
<file name="rss.png" server="students.acg.edu/www/" local="130802385870058135" remote="130774572000000000" Dst="2" />
<file name="spinner-2x.gif" server="students.acg.edu/www/" local="130802385901249919" remote="130774571400000000" Dst="2" />
<file name="spinner.gif" server="students.acg.edu/www/" local="130802385901259919" remote="130774571400000000" Dst="2" />
<file name="toggle-arrow-2x.png" server="students.acg.edu/www/" local="130802385901299921" remote="130774572000000000" Dst="2" />
<file name="toggle-arrow.png" server="students.acg.edu/www/" local="130802385902890012" remote="130774572000000000" Dst="2" />
<file name="uploader-icons-2x.png" server="students.acg.edu/www/" local="130802385902920014" remote="130774571400000000" Dst="2" />
<file name="uploader-icons.png" server="students.acg.edu/www/" local="130802385902990018" remote="130774571400000000" Dst="2" />
<file name="wpicons.png" server="students.acg.edu/www/" local="130802385906250205" remote="130774572000000000" Dst="2" />
<file name="wpicons-2x.png" server="students.acg.edu/www/" local="130802385906280206" remote="130774572000000000" Dst="2" />
<file name="wpspin-2x.gif" server="students.acg.edu/www/" local="130802385906450216" remote="130774572000000000" Dst="2" />
<file name="wpspin.gif" server="students.acg.edu/www/" local="130802385907970303" remote="130774572000000000" Dst="2" />
<file name="xit-2x.gif" server="students.acg.edu/www/" local="130802385907990304" remote="130774572000000000" Dst="2" />
<file name="xit.gif" server="students.acg.edu/www/" local="130802385908030306" remote="130774572000000000" Dst="2" />
</dwsync>